{
  "gpCode": "XXVII",
  "period": 27,
  "sitting": 159,
  "session": "27159",
  "mediathekURL": "https://www.parlament.gv.at/aktuelles/mediathek/XXVII/NRSITZ/159",
  "sessionMeta": {
    "ebene": 1,
    "text": "XXVII. Gesetzgebungsperiode | Aufzeichnung vom 19.05.2022",
    "title": "159. Sitzung des Nationalrates am 19.05.2022",
    "datetime": "19.05.2022",
    "type": "SESSION",
    "startinfo": "Der Livestream startete am<br>Donnerstag 19. Mai 2022 um 19:28 Uhr.",
    "untertitel": null,
    "medium": {
      "uuid": "b6a06630-3fa7-4d0a-bee8-692568d507b5",
      "ts": 1652988513,
      "streams": [
        "dirty",
        "dirty-sign"
      ]
    },
    "live": false,
    "ityp": "NRSITZ",
    "doktyp": "NRSITZ",
    "tabs": [
      {
        "id": "INFOS",
        "label": "Infos",
        "selected": true
      },
      {
        "id": "REDEZEITEN",
        "label": "Redezeiten",
        "selected": false
      },
      {
        "id": "PROTOKOLL",
        "label": "Protokoll",
        "selected": false
      },
      {
        "id": "ZURPERSON",
        "label": "Zur Person",
        "selected": false
      },
      {
        "id": "LINKS",
        "label": "Links",
        "selected": false
      }
    ]
  },
  "debatten": [
    {
      "debatte_id_teil": 1,
      "debatte_id": 300,
      "content": "Präsidium",
      "time": "2022-05-19T19:28:40",
      "ts": 1652988520,
      "uuid": "12ea625f-82f6-4793-bcf9-3d9d3e038b71",
      "info": "{\"text\":\"<div><h3>Präsidium</h3><br/>19:28:40</div>\"}",
      "links": "{\"text\":\"<div class=\\\"debatteSitzungLink\\\">Sitzungsseite: <a href=\\\"/gegenstand/XXVII/NRSITZ/159\\\">159. Sitzung</a></div>\"}",
      "redner": [
        {
          "time": "2022-05-19T19:28:40",
          "pad_intern": 35521,
          "name": "Norbert Hofer",
          "uuid": "ceef1136-65f0-48f5-9c51-7c1c7349560f",
          "ts": 1652988520,
          "std_id": 268256,
          "img": {
            "text": "Portraitfoto von Ing. Norbert Hofer",
            "url": "/dokument/bild/200696/20069631_384.jpg",
            "copyright": "Parlamentsdirektion/PHOTO SIMONIS",
            "mutdat": "2023-06-16T14:17:15"
          },
          "protokoll": "/dokument/XXVII/NRSITZ/159/A_-_19_28_34_00268256.html",
          "sourcePage": "https://www.parlament.gv.at/aktuelles/mediathek/XXVII/NRSITZ/159?DEBATTE=300&TS=1652988520",
          "video": {
            "hls": "https://parlament-live.mdn.ors.at/assets/6389a1b6-2d1c-42b2-b6a8-c1db18143467/hls/index.m3u8?startseconds=7&stopseconds=41",
            "mp4": "https://parlament-live.mdn.ors.at/assets/010e5dc4-4159-411d-a6b2-dbdcce47a7d0/010e5dc4-4159-411d-a6b2-dbdcce47a7d0.mp4",
            "mp3": "https://parlament-live.mdn.ors.at/assets/010e5dc4-4159-411d-a6b2-dbdcce47a7d0/010e5dc4-4159-411d-a6b2-dbdcce47a7d0.mp3",
            "startSeconds": 7,
            "stopSeconds": 41,
            "duration": 34
          }
        }
      ],
      "themen": []
    }
  ]
}